gevulot/__init__.py
gevulot/cli.py
gevulot/data/__init__.py
gevulot/data/repository.py
gevulot/gevulot.py
gevulot/lib/__init__.py
gevulot/lib/config.py
gevulot/metadata/__init__.py
gevulot/metadata/config.py
gevulot/metadata/graph.py
gevulot/metadata/indexing.py
gevulot/metadata/repository.py
gevulot/model.py
gevulot-0.0.1.dist-info/entry_points.txt
gevulot-0.0.1.dist-info/LICENSE
gevulot-0.0.1.dist-info/WHEEL
gevulot-0.0.1.dist-info/METADATA
gevulot-0.0.1.dist-info/RECORD
