Metadata-Version: 2.1
Name: gevulot
Version: 0.0.1
Summary: Virtual file system for managing computational graph metadata
Author: Sarasti Nishi
Author-email: sarasti.nishi@wormhole.digital
Requires-Python: >=3.9,<4.0
Classifier: Programming Language :: Python :: 3
Classifier: Programming Language :: Python :: 3.9
Classifier: Programming Language :: Python :: 3.10
Classifier: Programming Language :: Python :: 3.11
Requires-Dist: boto3 (>=1.28.48,<1.29.0)
Requires-Dist: click (>=8.1.7,<8.2.0)
Requires-Dist: joblib (>=1.3.2,<1.4.0)
Requires-Dist: loguru (>=0.7.2,<0.8.0)
Requires-Dist: minio (>=7.1.16,<7.2.0)
Requires-Dist: orjson (>=3.9.9,<3.10.0)
Requires-Dist: pyhocon (>=0.3.60,<0.4.0)
Requires-Dist: tabulate (>=0.9.0,<0.10.0)
Requires-Dist: tqdm (>=4.66.1,<4.67.0)
